{
  "backgroundColor": "#FFFFFF",
  "borderColor": "#E0DEDE",
  "borderRadius": "{{appsmith.theme.borderRadius.appBorderRadius}}",
  "borderWidth": "1",
  "bottomRow": 234,
  "boxShadow": "{{appsmith.theme.boxShadow.appBoxShadow}}",
  "defaultModel": "{{\n  {\n    \"observed_variables\": QueryModelOutput.data?.fileData ? JSON.parse(QueryModelOutput.data.fileData)[0].variables_used.non_compliant : [],\n    \"outcome_disparity_metrics\": [\n      {\n        \"segment\": \"Gender: Female\",\n        \"metric\": \"Mean Predicted Tenure (YearsWithCurrManager)\",\n        \"disparity\": \"-1.8 years vs Baseline (Male)\",\n        \"threshold\": \"Exceeds 1.0 year tolerance\",\n        \"confidence\": \"High\",\n        \"mitigation\": \"Review feature weights for 'Gender' and 'MaritalStatus'. Consider dropping these variables and retraining.\"\n      }\n    ]\n  }\n}}",
  "dynamicBindingPathList": [
    {
      "key": "theme"
    },
    {
      "key": "borderRadius"
    },
    {
      "key": "boxShadow"
    },
    {
      "key": "defaultModel"
    }
  ],
  "dynamicHeight": "FIXED",
  "dynamicTriggerPathList": [
    {
      "key": "onResetClick"
    }
  ],
  "events": [
    "onResetClick"
  ],
  "isCanvas": false,
  "isLoading": false,
  "isSearchWildcard": true,
  "isVisible": true,
  "key": "6sgi5oph5m",
  "leftColumn": 2,
  "maxDynamicHeight": 9000,
  "minDynamicHeight": 4,
  "mobileBottomRow": 195,
  "mobileLeftColumn": 2,
  "mobileRightColumn": 25,
  "mobileTopRow": 165,
  "needsErrorInfo": false,
  "onResetClick": "{{showAlert('Successfully reset!!', '');}}",
  "parentColumnSpace": 19.59375,
  "parentId": "0",
  "parentRowSpace": 10,
  "renderMode": "CANVAS",
  "rightColumn": 62,
  "srcDoc": {
    "css": "@charset \"UTF-8\";\n.dashboard-frame.risk-signals-frame {\n  font-family: \"Segoe UI\", Tahoma, Geneva, Verdana, sans-serif;\n  background-color: #ffffff;\n  color: #2c3e50;\n  padding: 24px;\n  border-radius: 8px;\n  border: 1px solid #e9ecef;\n  box-shadow: 0 2px 4px rgba(0, 0, 0, 0.02);\n  margin-bottom: 24px;\n}\n\n.section-header {\n  margin-bottom: 24px;\n  border-bottom: 1px solid #e9ecef;\n  padding-bottom: 12px;\n  text-align: center;\n}\n\n.section-header h2 {\n  margin: 0 0 5px 0;\n  font-size: 1.9rem;\n  color: #2c3e50;\n}\n\n.section-header p {\n  margin: 0;\n  color: #7f8c8d;\n  font-size: 0.95rem;\n}\n\n.signals-grid {\n  display: grid;\n  grid-template-columns: repeat(auto-fit, minmax(350px, 1fr));\n  gap: 20px;\n}\n\n.signal-card {\n  background: #fdfdfd;\n  border: 1px solid #e9ecef;\n  border-top: 4px solid #e9ecef;\n  border-radius: 6px;\n  padding: 20px;\n  display: flex;\n  flex-direction: column;\n}\n\n.card-header {\n  display: flex;\n  justify-content: space-between;\n  align-items: center;\n  margin-bottom: 8px;\n}\n\n.card-header h3 {\n  margin: 0;\n  font-size: 1.05rem;\n  color: #34495e;\n}\n\n.card-description {\n  margin: 0 0 16px 0;\n  font-size: 0.85rem;\n  color: #7f8c8d;\n  line-height: 1.4;\n}\n\n.feature-list {\n  margin: 0;\n  padding: 0;\n  list-style-type: none;\n  flex-grow: 1;\n}\n\n.feature-list li {\n  font-size: 0.95rem;\n  color: #2c3e50;\n  padding: 8px 12px;\n  background: #ffffff;\n  border: 1px solid #e9ecef;\n  border-radius: 4px;\n  margin-bottom: 8px;\n  display: flex;\n  align-items: center;\n}\n\n.feature-list li::before {\n  content: \"•\";\n  color: #e74c3c;\n  font-weight: bold;\n  margin-right: 8px;\n  font-size: 1.2rem;\n}\n\n.evidence-footer {\n  margin-top: 16px;\n  padding-top: 12px;\n  border-top: 1px dashed #e9ecef;\n  font-size: 0.85rem;\n  color: #7f8c8d;\n}\n\n.evidence-footer strong {\n  color: #2c3e50;\n}\n\n.placeholder-state {\n  padding: 20px;\n  background: #f8f9fa;\n  border: 1px dashed #dee2e6;\n  border-radius: 4px;\n  text-align: center;\n  color: #7f8c8d;\n  font-size: 0.9rem;\n  flex-grow: 1;\n  display: flex;\n  align-items: center;\n  justify-content: center;\n}\n\n/* Disparity Specific Styles */\n.disparity-container {\n  flex-grow: 1;\n  display: flex;\n  flex-direction: column;\n  gap: 12px;\n}\n\n.disparity-item {\n  background: #fff5f5;\n  border: 1px solid #ffe3e3;\n  border-radius: 4px;\n  padding: 12px;\n}\n\n.disparity-header {\n  display: flex;\n  justify-content: space-between;\n  margin-bottom: 8px;\n  font-size: 0.9rem;\n}\n\n.disparity-header strong {\n  color: #c0392b;\n}\n\n.disparity-metric {\n  font-size: 0.85rem;\n  color: #2c3e50;\n  margin-bottom: 4px;\n}\n\n.disparity-threshold {\n  font-size: 0.8rem;\n  color: #7f8c8d;\n  font-style: italic;\n  margin-bottom: 8px;\n  padding-bottom: 8px;\n  border-bottom: 1px dashed #f5c6cb;\n}\n\n.disparity-mitigation {\n  font-size: 0.85rem;\n  color: #2c3e50;\n  background: #ffffff;\n  padding: 8px;\n  border-radius: 4px;\n  border: 1px solid #e9ecef;\n}\n\n.disparity-mitigation strong {\n  color: #34495e;\n}\n\n/* Modifiers */\n.border-critical {\n  border-top-color: #e74c3c;\n}\n\n.border-warning {\n  border-top-color: #f39c12;\n}\n\n.border-neutral {\n  border-top-color: #95a5a6;\n}\n\n.badge {\n  padding: 4px 8px;\n  border-radius: 4px;\n  font-size: 0.85rem;\n  font-weight: bold;\n}\n\n.badge-critical {\n  background: #f8d7da;\n  color: #721c24;\n  border: 1px solid #f5c6cb;\n}\n\n.badge-warning {\n  background: #fff3cd;\n  color: #856404;\n  border: 1px solid #ffeeba;\n}\n\n.badge-neutral {\n  background: #e2e3e5;\n  color: #383d41;\n  border: 1px solid #d6d8db;\n}",
    "html": "<div class=\"dashboard-frame risk-signals-frame\">\n    <header class=\"section-header\">\n        <h2>Model Risk Signals (Observed & Inferred)</h2>\n        <p>Categorized exposure, bias, and proxy indicators</p>\n    </header>\n\n    <div class=\"signals-grid\">\n        <div class=\"signal-card border-critical\">\n            <div class=\"card-header\">\n                <h3>Protected Attribute Exposure Signals</h3>\n                <span class=\"badge badge-critical\" id=\"count-protected\">0</span>\n            </div>\n            <p class=\"card-description\">Direct ingestion of legally or ethically protected classes.</p>\n            <ul class=\"feature-list\" id=\"list-protected\">\n                <li>Scanning...</li>\n            </ul>\n            <div class=\"evidence-footer\">Confidence: <strong>High</strong> (Observed Input)</div>\n        </div>\n\n        <div class=\"signal-card border-warning\">\n            <div class=\"card-header\">\n                <h3>Proxy & Inferred Attribute Signals</h3>\n                <span class=\"badge badge-warning\" id=\"count-proxy\">0</span>\n            </div>\n            <p class=\"card-description\">Features capable of inferring protected attributes via correlation.</p>\n            <ul class=\"feature-list\" id=\"list-proxy\">\n                <li>Scanning...</li>\n            </ul>\n            <div class=\"evidence-footer\">Confidence: <strong>Medium</strong> (Inferred Correlation)</div>\n        </div>\n\n        <div class=\"signal-card border-warning\">\n            <div class=\"card-header\">\n                <h3>Input Sensitivity & Bias Signals</h3>\n                <span class=\"badge badge-warning\" id=\"count-bias\">0</span>\n            </div>\n            <p class=\"card-description\">Variables known to skew outcomes or introduce socioeconomic bias.</p>\n            <ul class=\"feature-list\" id=\"list-bias\">\n                <li>Scanning...</li>\n            </ul>\n             <div class=\"evidence-footer\">Confidence: <strong>High</strong> (Observed Input)</div>\n        </div>\n\n        <div class=\"signal-card border-critical\" id=\"disparity-card\">\n            <div class=\"card-header\">\n                <h3>Outcome Disparity Signals</h3>\n                <span class=\"badge badge-critical\" id=\"count-disparity\">0</span>\n            </div>\n            <p class=\"card-description\">Performance disparities across protected demographic segments.</p>\n            \n            <div id=\"disparity-content\" class=\"disparity-container\">\n                </div>\n            \n            <div class=\"evidence-footer\">Confidence: <strong id=\"disparity-confidence\">Pending</strong> (Runtime Evaluation)</div>\n        </div>\n    </div>\n</div>",
    "js": "appsmith.onReady(() => {\n  renderRiskSignals();\n});\nappsmith.onModelChange(() => {\n  renderRiskSignals();\n});\nfunction renderRiskSignals() {\n  const data = appsmith.model;\n  const observedVariables = data.observed_variables || [];\n  const disparityMetrics = data.outcome_disparity_metrics || [];\n\n  // 1. Categorization Logic\n  const protectedCategories = [\"Gender\", \"Age\", \"Ethnicity\", \"MaritalStatus\"];\n  const biasCategories = [\"Salary\", \"JobRole\", \"StockOptionLevel\", \"OverTime\", \"Department\"];\n  const proxyCategories = [\"DistanceFromHome (KM)\", \"State\", \"Education\", \"EducationField\"];\n  const foundProtected = observedVariables.filter(v => protectedCategories.includes(v));\n  const foundBias = observedVariables.filter(v => biasCategories.includes(v));\n  const foundProxy = observedVariables.filter(v => proxyCategories.includes(v));\n\n  // 2. Helper to render attribute lists\n  function populateList(elementId, countId, items) {\n    const listEl = document.getElementById(elementId);\n    const countEl = document.getElementById(countId);\n    countEl.textContent = items.length;\n    listEl.innerHTML = \"\";\n    if (items.length === 0) {\n      listEl.innerHTML = `<li><span style=\"color:#7f8c8d; font-style:italic;\">No signals detected in this category.</span></li>`;\n    } else {\n      items.forEach(item => {\n        const li = document.createElement('li');\n        li.textContent = item;\n        listEl.appendChild(li);\n      });\n    }\n  }\n\n  // Populate the first three cards\n  populateList('list-protected', 'count-protected', foundProtected);\n  populateList('list-bias', 'count-bias', foundBias);\n  populateList('list-proxy', 'count-proxy', foundProxy);\n\n  // 3. Render Outcome Disparity Signals\n  populateDisparitySignals(disparityMetrics);\n}\nfunction populateDisparitySignals(metrics) {\n  const container = document.getElementById('disparity-content');\n  const countEl = document.getElementById('count-disparity');\n  const confidenceEl = document.getElementById('disparity-confidence');\n  countEl.textContent = metrics.length;\n  container.innerHTML = \"\";\n  if (metrics.length === 0) {\n    container.innerHTML = `<div class=\"placeholder-state\"><em>Awaiting runtime evaluation harness integration.</em></div>`;\n    document.getElementById('disparity-card').className = \"signal-card border-neutral\";\n    countEl.className = \"badge badge-neutral\";\n    return;\n  }\n  metrics.forEach(item => {\n    confidenceEl.textContent = item.confidence;\n    const div = document.createElement('div');\n    div.className = \"disparity-item\";\n    div.innerHTML = `\n            <div class=\"disparity-header\">\n                <strong>Impacted Segment: ${item.segment}</strong>\n            </div>\n            <div class=\"disparity-metric\">\n                <strong>Observed Delta:</strong> ${item.disparity}\n            </div>\n            <div class=\"disparity-threshold\">\n                ${item.threshold}\n            </div>\n            <div class=\"disparity-mitigation\">\n                <strong>Suggested Mitigation:</strong><br>\n                ${item.mitigation}\n            </div>\n        `;\n    container.appendChild(div);\n  });\n}"
  },
  "theme": "{{appsmith.theme}}",
  "topRow": 176,
  "type": "CUSTOM_WIDGET",
  "uncompiledSrcDoc": {
    "css": ".dashboard-frame.risk-signals-frame {\n    font-family: 'Segoe UI', Tahoma, Geneva, Verdana, sans-serif;\n    background-color: #ffffff;\n    color: #2c3e50;\n    padding: 24px;\n    border-radius: 8px;\n    border: 1px solid #e9ecef;\n    box-shadow: 0 2px 4px rgba(0,0,0,0.02);\n    margin-bottom: 24px;\n}\n\n.section-header {\n    margin-bottom: 24px;\n    border-bottom: 1px solid #e9ecef;\n    padding-bottom: 12px;\n\ttext-align: center;\n}\n\n.section-header h2 {\n    margin: 0 0 5px 0;\n    font-size: 1.9rem;\n    color: #2c3e50;\n}\n\n.section-header p {\n    margin: 0;\n    color: #7f8c8d;\n    font-size: 0.95rem;\n}\n\n.signals-grid {\n    display: grid;\n    grid-template-columns: repeat(auto-fit, minmax(350px, 1fr));\n    gap: 20px;\n}\n\n.signal-card {\n    background: #fdfdfd;\n    border: 1px solid #e9ecef;\n    border-top: 4px solid #e9ecef;\n    border-radius: 6px;\n    padding: 20px;\n    display: flex;\n    flex-direction: column;\n}\n\n.card-header {\n    display: flex;\n    justify-content: space-between;\n    align-items: center;\n    margin-bottom: 8px;\n}\n\n.card-header h3 {\n    margin: 0;\n    font-size: 1.05rem;\n    color: #34495e;\n}\n\n.card-description {\n    margin: 0 0 16px 0;\n    font-size: 0.85rem;\n    color: #7f8c8d;\n    line-height: 1.4;\n}\n\n.feature-list {\n    margin: 0;\n    padding: 0;\n    list-style-type: none;\n    flex-grow: 1;\n}\n\n.feature-list li {\n    font-size: 0.95rem;\n    color: #2c3e50;\n    padding: 8px 12px;\n    background: #ffffff;\n    border: 1px solid #e9ecef;\n    border-radius: 4px;\n    margin-bottom: 8px;\n    display: flex;\n    align-items: center;\n}\n\n.feature-list li::before {\n    content: \"•\";\n    color: #e74c3c;\n    font-weight: bold;\n    margin-right: 8px;\n    font-size: 1.2rem;\n}\n\n.evidence-footer {\n    margin-top: 16px;\n    padding-top: 12px;\n    border-top: 1px dashed #e9ecef;\n    font-size: 0.85rem;\n    color: #7f8c8d;\n}\n\n.evidence-footer strong {\n    color: #2c3e50;\n}\n\n.placeholder-state {\n    padding: 20px;\n    background: #f8f9fa;\n    border: 1px dashed #dee2e6;\n    border-radius: 4px;\n    text-align: center;\n    color: #7f8c8d;\n    font-size: 0.9rem;\n    flex-grow: 1;\n    display: flex;\n    align-items: center;\n    justify-content: center;\n}\n\n/* Disparity Specific Styles */\n.disparity-container {\n    flex-grow: 1;\n    display: flex;\n    flex-direction: column;\n    gap: 12px;\n}\n\n.disparity-item {\n    background: #fff5f5;\n    border: 1px solid #ffe3e3;\n    border-radius: 4px;\n    padding: 12px;\n}\n\n.disparity-header {\n    display: flex;\n    justify-content: space-between;\n    margin-bottom: 8px;\n    font-size: 0.9rem;\n}\n\n.disparity-header strong {\n    color: #c0392b;\n}\n\n.disparity-metric {\n    font-size: 0.85rem;\n    color: #2c3e50;\n    margin-bottom: 4px;\n}\n\n.disparity-threshold {\n    font-size: 0.8rem;\n    color: #7f8c8d;\n    font-style: italic;\n    margin-bottom: 8px;\n    padding-bottom: 8px;\n    border-bottom: 1px dashed #f5c6cb;\n}\n\n.disparity-mitigation {\n    font-size: 0.85rem;\n    color: #2c3e50;\n    background: #ffffff;\n    padding: 8px;\n    border-radius: 4px;\n    border: 1px solid #e9ecef;\n}\n\n.disparity-mitigation strong {\n    color: #34495e;\n}\n\n/* Modifiers */\n.border-critical { border-top-color: #e74c3c; }\n.border-warning { border-top-color: #f39c12; }\n.border-neutral { border-top-color: #95a5a6; }\n\n.badge {\n    padding: 4px 8px;\n    border-radius: 4px;\n    font-size: 0.85rem;\n    font-weight: bold;\n}\n.badge-critical { background: #f8d7da; color: #721c24; border: 1px solid #f5c6cb; }\n.badge-warning { background: #fff3cd; color: #856404; border: 1px solid #ffeeba; }\n.badge-neutral { background: #e2e3e5; color: #383d41; border: 1px solid #d6d8db; }",
    "html": "<div class=\"dashboard-frame risk-signals-frame\">\n    <header class=\"section-header\">\n        <h2>Model Risk Signals (Observed & Inferred)</h2>\n        <p>Categorized exposure, bias, and proxy indicators</p>\n    </header>\n\n    <div class=\"signals-grid\">\n        <div class=\"signal-card border-critical\">\n            <div class=\"card-header\">\n                <h3>Protected Attribute Exposure Signals</h3>\n                <span class=\"badge badge-critical\" id=\"count-protected\">0</span>\n            </div>\n            <p class=\"card-description\">Direct ingestion of legally or ethically protected classes.</p>\n            <ul class=\"feature-list\" id=\"list-protected\">\n                <li>Scanning...</li>\n            </ul>\n            <div class=\"evidence-footer\">Confidence: <strong>High</strong> (Observed Input)</div>\n        </div>\n\n        <div class=\"signal-card border-warning\">\n            <div class=\"card-header\">\n                <h3>Proxy & Inferred Attribute Signals</h3>\n                <span class=\"badge badge-warning\" id=\"count-proxy\">0</span>\n            </div>\n            <p class=\"card-description\">Features capable of inferring protected attributes via correlation.</p>\n            <ul class=\"feature-list\" id=\"list-proxy\">\n                <li>Scanning...</li>\n            </ul>\n            <div class=\"evidence-footer\">Confidence: <strong>Medium</strong> (Inferred Correlation)</div>\n        </div>\n\n        <div class=\"signal-card border-warning\">\n            <div class=\"card-header\">\n                <h3>Input Sensitivity & Bias Signals</h3>\n                <span class=\"badge badge-warning\" id=\"count-bias\">0</span>\n            </div>\n            <p class=\"card-description\">Variables known to skew outcomes or introduce socioeconomic bias.</p>\n            <ul class=\"feature-list\" id=\"list-bias\">\n                <li>Scanning...</li>\n            </ul>\n             <div class=\"evidence-footer\">Confidence: <strong>High</strong> (Observed Input)</div>\n        </div>\n\n        <div class=\"signal-card border-critical\" id=\"disparity-card\">\n            <div class=\"card-header\">\n                <h3>Outcome Disparity Signals</h3>\n                <span class=\"badge badge-critical\" id=\"count-disparity\">0</span>\n            </div>\n            <p class=\"card-description\">Performance disparities across protected demographic segments.</p>\n            \n            <div id=\"disparity-content\" class=\"disparity-container\">\n                </div>\n            \n            <div class=\"evidence-footer\">Confidence: <strong id=\"disparity-confidence\">Pending</strong> (Runtime Evaluation)</div>\n        </div>\n    </div>\n</div>",
    "js": "appsmith.onReady(() => {\n    renderRiskSignals();\n});\n\nappsmith.onModelChange(() => {\n    renderRiskSignals();\n});\n\nfunction renderRiskSignals() {\n    const data = appsmith.model;\n    const observedVariables = data.observed_variables || [];\n    const disparityMetrics = data.outcome_disparity_metrics || [];\n\n    // 1. Categorization Logic\n    const protectedCategories = [\"Gender\", \"Age\", \"Ethnicity\", \"MaritalStatus\"];\n    const biasCategories = [\"Salary\", \"JobRole\", \"StockOptionLevel\", \"OverTime\", \"Department\"];\n    const proxyCategories = [\"DistanceFromHome (KM)\", \"State\", \"Education\", \"EducationField\"];\n\n    const foundProtected = observedVariables.filter(v => protectedCategories.includes(v));\n    const foundBias = observedVariables.filter(v => biasCategories.includes(v));\n    const foundProxy = observedVariables.filter(v => proxyCategories.includes(v));\n\n    // 2. Helper to render attribute lists\n    function populateList(elementId, countId, items) {\n        const listEl = document.getElementById(elementId);\n        const countEl = document.getElementById(countId);\n        \n        countEl.textContent = items.length;\n        listEl.innerHTML = \"\";\n\n        if (items.length === 0) {\n            listEl.innerHTML = `<li><span style=\"color:#7f8c8d; font-style:italic;\">No signals detected in this category.</span></li>`;\n        } else {\n            items.forEach(item => {\n                const li = document.createElement('li');\n                li.textContent = item;\n                listEl.appendChild(li);\n            });\n        }\n    }\n\n    // Populate the first three cards\n    populateList('list-protected', 'count-protected', foundProtected);\n    populateList('list-bias', 'count-bias', foundBias);\n    populateList('list-proxy', 'count-proxy', foundProxy);\n\n    // 3. Render Outcome Disparity Signals\n    populateDisparitySignals(disparityMetrics);\n}\n\nfunction populateDisparitySignals(metrics) {\n    const container = document.getElementById('disparity-content');\n    const countEl = document.getElementById('count-disparity');\n    const confidenceEl = document.getElementById('disparity-confidence');\n    \n    countEl.textContent = metrics.length;\n    container.innerHTML = \"\";\n\n    if (metrics.length === 0) {\n        container.innerHTML = `<div class=\"placeholder-state\"><em>Awaiting runtime evaluation harness integration.</em></div>`;\n        document.getElementById('disparity-card').className = \"signal-card border-neutral\";\n        countEl.className = \"badge badge-neutral\";\n        return;\n    }\n\n    metrics.forEach(item => {\n        confidenceEl.textContent = item.confidence;\n        \n        const div = document.createElement('div');\n        div.className = \"disparity-item\";\n        div.innerHTML = `\n            <div class=\"disparity-header\">\n                <strong>Impacted Segment: ${item.segment}</strong>\n            </div>\n            <div class=\"disparity-metric\">\n                <strong>Observed Delta:</strong> ${item.disparity}\n            </div>\n            <div class=\"disparity-threshold\">\n                ${item.threshold}\n            </div>\n            <div class=\"disparity-mitigation\">\n                <strong>Suggested Mitigation:</strong><br>\n                ${item.mitigation}\n            </div>\n        `;\n        container.appendChild(div);\n    });\n}"
  },
  "version": 1,
  "widgetId": "xkh8i7le4r",
  "widgetName": "Custom4"
}